sdmpy/__init__.py
sdmpy/bdf.py
sdmpy/bdf_tmp.py
sdmpy/bintab.py
sdmpy/calib.py
sdmpy/mime.py
sdmpy/pulsar.py
sdmpy/scan.py
sdmpy/sdm.py
sdmpy/xsd/ACAPolarization.xsd
sdmpy/xsd/ASDM.xsd
sdmpy/xsd/ASDMBinaryTable.xsd
sdmpy/xsd/AccumMode.xsd
sdmpy/xsd/AlmaRadiometerTable.xsd
sdmpy/xsd/AnnotationTable.xsd
sdmpy/xsd/AntennaMake.xsd
sdmpy/xsd/AntennaMotionPattern.xsd
sdmpy/xsd/AntennaTable.xsd
sdmpy/xsd/AntennaType.xsd
sdmpy/xsd/AssociatedCalNature.xsd
sdmpy/xsd/AssociatedFieldNature.xsd
sdmpy/xsd/AtmPhaseCorrection.xsd
sdmpy/xsd/AxisName.xsd
sdmpy/xsd/BasebandName.xsd
sdmpy/xsd/BaselineReferenceCode.xsd
sdmpy/xsd/BinaryDataFlags.xsd
sdmpy/xsd/CalAmpliTable.xsd
sdmpy/xsd/CalAntennaSolutionsTable.xsd
sdmpy/xsd/CalAppPhaseTable.xsd
sdmpy/xsd/CalAtmosphereTable.xsd
sdmpy/xsd/CalBandpassTable.xsd
sdmpy/xsd/CalCurveTable.xsd
sdmpy/xsd/CalCurveType.xsd
sdmpy/xsd/CalDataOrigin.xsd
sdmpy/xsd/CalDataTable.xsd
sdmpy/xsd/CalDelayTable.xsd
sdmpy/xsd/CalDeviceTable.xsd
sdmpy/xsd/CalFluxTable.xsd
sdmpy/xsd/CalFocusModelTable.xsd
sdmpy/xsd/CalFocusTable.xsd
sdmpy/xsd/CalGainTable.xsd
sdmpy/xsd/CalHolographyTable.xsd
sdmpy/xsd/CalPhaseTable.xsd
sdmpy/xsd/CalPointingModelTable.xsd
sdmpy/xsd/CalPointingTable.xsd
sdmpy/xsd/CalPositionTable.xsd
sdmpy/xsd/CalPrimaryBeamTable.xsd
sdmpy/xsd/CalReductionTable.xsd
sdmpy/xsd/CalSeeingTable.xsd
sdmpy/xsd/CalType.xsd
sdmpy/xsd/CalWVRTable.xsd
sdmpy/xsd/CalibrationDevice.xsd
sdmpy/xsd/CalibrationFunction.xsd
sdmpy/xsd/CalibrationMode.xsd
sdmpy/xsd/CalibrationSet.xsd
sdmpy/xsd/CommonEntity.xsd
sdmpy/xsd/ConfigDescriptionTable.xsd
sdmpy/xsd/CorrelationBit.xsd
sdmpy/xsd/CorrelationMode.xsd
sdmpy/xsd/CorrelatorCalibration.xsd
sdmpy/xsd/CorrelatorModeTable.xsd
sdmpy/xsd/CorrelatorName.xsd
sdmpy/xsd/CorrelatorType.xsd
sdmpy/xsd/DataContent.xsd
sdmpy/xsd/DataDescriptionTable.xsd
sdmpy/xsd/DataScale.xsd
sdmpy/xsd/DelayModelFixedParametersTable.xsd
sdmpy/xsd/DelayModelTable.xsd
sdmpy/xsd/DelayModelVariableParametersTable.xsd
sdmpy/xsd/DetectorBandType.xsd
sdmpy-1.71.2.dist-info/METADATA
sdmpy-1.71.2.dist-info/WHEEL
sdmpy-1.71.2.dist-info/top_level.txt
sdmpy-1.71.2.dist-info/RECORD
