Metadata-Version: 2.1
Name: sdmpy
Version: 1.71.2
Summary: Python for ALMA/VLA Science Data Model
Home-page: http://github.com/demorest/sdmpy
Author: Paul Demorest
Author-email: pdemores@nrao.edu
Requires-Dist: lxml
Requires-Dist: numpy
Requires-Dist: future
Requires-Dist: progressbar2
